dev/__init__.py
dev/django/__init__.py
dev/django/manage.py
dev/django/mypy.ini
dev/django/core/__init__.py
dev/django/core/asgi.py
dev/django/core/settings.py
dev/django/core/urls.py
dev/django/core/wsgi.py
dev/django/misc/__init__.py
dev/django/misc/prepare_swappable_migration.py
revy/__init__.py
revy/__main__.py
revy/__version__.py
revy/_argparse.py
revy/context.py
revy/globals.py
revy/py.typed
revy/storages.py
revy/abc/__init__.py
revy/abc/attribute_delta.py
revy/abc/delta.py
revy/abc/lazy_revision.py
revy/abc/object_delta.py
revy/abc/revision.py
revy/contrib/__init__.py
revy/contrib/django/__init__.py
revy/contrib/django/_typing.py
revy/contrib/django/_typing_ext.py
revy/contrib/django/admin.py
revy/contrib/django/aggregates.py
revy/contrib/django/apps.py
revy/contrib/django/deletion.py
revy/contrib/django/models.py
revy/contrib/django/patcher.py
revy/contrib/django/setup.py
revy/contrib/django/tests.py
revy/contrib/django/utils.py
revy/contrib/django/views.py
revy/contrib/django/conf/__init__.py
revy/contrib/django/conf/settings.py
revy/contrib/django/migrations/0001_initial.py
revy/contrib/django/migrations/__init__.py
revy/dataclasses/__init__.py
revy/dataclasses/metadata.py
revy-1.0.0a17.dist-info/LICENSE
revy-1.0.0a17.dist-info/METADATA
revy-1.0.0a17.dist-info/WHEEL
revy-1.0.0a17.dist-info/top_level.txt
revy-1.0.0a17.dist-info/zip-safe
revy-1.0.0a17.dist-info/RECORD
