Metadata-Version: 2.1
Name: revy
Version: 1.0.0a17
Summary: A toolkit for building revision control systems.
Home-page: https://github.com/ertgl/revy/
Author: Ertuğrul Noyan Keremoğlu
Author-email: ertugkeremoglu@gmail.com
License: MIT
Classifier: Framework :: Django
Classifier: Intended Audience :: Developers
Classifier: License :: OSI Approved :: MIT License
Classifier: Natural Language :: English
Classifier: Operating System :: OS Independent
Classifier: Programming Language :: Python :: 3
Classifier: Topic :: Software Development :: Libraries :: Python Modules
Classifier: Topic :: Utilities
Classifier: Typing :: Typed
License-File: LICENSE
Requires-Dist: asgiref
Requires-Dist: stackholm
